README.md
setup.py
enhance_okta_jwt.egg-info/PKG-INFO
enhance_okta_jwt.egg-info/SOURCES.txt
enhance_okta_jwt.egg-info/dependency_links.txt
enhance_okta_jwt.egg-info/requires.txt
enhance_okta_jwt.egg-info/top_level.txt
okta_jwt/__init__.py
okta_jwt/exceptions.py
okta_jwt/jwt.py
okta_jwt/utils.py