Metadata-Version: 2.1
Name: enhance-okta-jwt
Version: 1.3.5.4
Summary: Okta JWT Access Token verifier, fork and update
Home-page: https://github.com/luohuazju/okta_jwt
Author: Hua Luo fork and update
Author-email: luohuazju@gmail.com
License: UNKNOWN
Platform: UNKNOWN
Classifier: Development Status :: 5 - Production/Stable
Classifier: Intended Audience :: Developers
Classifier: Natural Language :: English
Classifier: License :: OSI Approved :: MIT License
Classifier: Programming Language :: Python :: 3.6
Classifier: Programming Language :: Python :: Implementation :: PyPy
Classifier: Topic :: Utilities
